uipath_langchain/__init__.py
uipath_langchain/middlewares.py
uipath_langchain/_cli/__init__.py
uipath_langchain/_cli/cli_init.py
uipath_langchain/_cli/cli_new.py
uipath_langchain/_cli/cli_run.py
uipath_langchain/_cli/_runtime/_context.py
uipath_langchain/_cli/_runtime/_escalation.py
uipath_langchain/_cli/_runtime/_exception.py
uipath_langchain/_cli/_runtime/_input.py
uipath_langchain/_cli/_runtime/_output.py
uipath_langchain/_cli/_runtime/_runtime.py
uipath_langchain/_cli/_templates/langgraph.json.template
uipath_langchain/_cli/_templates/main.py.template
uipath_langchain/_cli/_utils/_graph.py
uipath_langchain/_utils/__init__.py
uipath_langchain/_utils/_request_mixin.py
uipath_langchain/_utils/_settings.py
uipath_langchain/_utils/_sleep_policy.py
uipath_langchain/chat/__init__.py
uipath_langchain/chat/models.py
uipath_langchain/embeddings/__init__.py
uipath_langchain/embeddings/embeddings.py
uipath_langchain/retrievers/__init__.py
uipath_langchain/retrievers/context_grounding_retriever.py
uipath_langchain/tracers/AsyncUiPathTracer.py
uipath_langchain/tracers/__init__.py
uipath_langchain/tracers/_events.py
uipath_langchain/tracers/_instrument_traceable.py
uipath_langchain/tracers/_utils.py
uipath_langchain/vectorstores/__init__.py
uipath_langchain/vectorstores/context_grounding_vectorstore.py
uipath_langchain_nightly-0.0.111.dev1000980140.dist-info/METADATA
uipath_langchain_nightly-0.0.111.dev1000980140.dist-info/WHEEL
uipath_langchain_nightly-0.0.111.dev1000980140.dist-info/entry_points.txt
uipath_langchain_nightly-0.0.111.dev1000980140.dist-info/licenses/LICENSE
uipath_langchain_nightly-0.0.111.dev1000980140.dist-info/RECORD
