Metadata-Version: 2.4
Name: uipath-langchain-nightly
Version: 0.0.111.dev1000980140
Summary: UiPath Langchain
Project-URL: Homepage, https://uipath.com
Project-URL: Repository, https://github.com/UiPath/uipath-langchain-python
Project-URL: Documentation, https://uipath.github.io/uipath-python/
Maintainer-email: Marius Cosareanu <marius.cosareanu@uipath.com>, Cristian Pufu <cristian.pufu@uipath.com>
License-File: LICENSE
Classifier: Development Status :: 3 - Alpha
Classifier: Intended Audience :: Developers
Classifier: Programming Language :: Python :: 3.10
Classifier: Programming Language :: Python :: 3.11
Classifier: Programming Language :: Python :: 3.12
Classifier: Topic :: Software Development :: Build Tools
Requires-Python: >=3.10
Requires-Dist: httpx>=0.27.0
Requires-Dist: langchain-community>=0.3.21
Requires-Dist: langchain-core>=0.3.34
Requires-Dist: langchain-openai>=0.3.3
Requires-Dist: langchain>=0.3.4
Requires-Dist: langgraph-checkpoint-sqlite>=2.0.3
Requires-Dist: langgraph>=0.2.70
Requires-Dist: openai>=1.65.5
Requires-Dist: pydantic-settings>=2.6.0
Requires-Dist: python-dotenv>=1.0.1
Requires-Dist: uipath-nightly<2.0.63.dev1003970000,>=2.0.63.dev1003960000
Provides-Extra: langchain
Requires-Dist: uipath-langchain>=0.0.2; extra == 'langchain'
